hgj_download_center
